<annotation>
	<folder>images</folder>
	<filename>setg_00065.jpg</filename>
	<path>/mnt/hard_data/GitHub/bite_selection_package/data/bounding_boxes/images/setg_00065.jpg</path>
	<source>
		<database>Unknown</database>
	</source>
	<size>
		<width>1920</width>
		<height>1080</height>
		<depth>3</depth>
	</size>
	<segmented>0</segmented>
	<object>
		<name>bell_pepper</name>
		<pose>Unspecified</pose>
		<truncated>0</truncated>
		<difficult>0</difficult>
		<bndbox>
			<xmin>754</xmin>
			<ymin>286</ymin>
			<xmax>1029</xmax>
			<ymax>548</ymax>
		</bndbox>
	</object>
	<object>
		<name>bell_pepper</name>
		<pose>Unspecified</pose>
		<truncated>0</truncated>
		<difficult>0</difficult>
		<bndbox>
			<xmin>1114</xmin>
			<ymin>588</ymin>
			<xmax>1459</xmax>
			<ymax>961</ymax>
		</bndbox>
	</object>
	<object>
		<name>bell_pepper</name>
		<pose>Unspecified</pose>
		<truncated>0</truncated>
		<difficult>0</difficult>
		<bndbox>
			<xmin>1269</xmin>
			<ymin>135</ymin>
			<xmax>1540</xmax>
			<ymax>366</ymax>
		</bndbox>
	</object>
	<object>
		<name>bell_pepper</name>
		<pose>Unspecified</pose>
		<truncated>0</truncated>
		<difficult>0</difficult>
		<bndbox>
			<xmin>647</xmin>
			<ymin>11</ymin>
			<xmax>870</xmax>
			<ymax>268</ymax>
		</bndbox>
	</object>
	<object>
		<name>blackberry</name>
		<pose>Unspecified</pose>
		<truncated>0</truncated>
		<difficult>0</difficult>
		<bndbox>
			<xmin>965</xmin>
			<ymin>203</ymin>
			<xmax>1127</xmax>
			<ymax>343</ymax>
		</bndbox>
	</object>
	<object>
		<name>broccoli</name>
		<pose>Unspecified</pose>
		<truncated>0</truncated>
		<difficult>0</difficult>
		<bndbox>
			<xmin>1154</xmin>
			<ymin>321</ymin>
			<xmax>1430</xmax>
			<ymax>590</ymax>
		</bndbox>
	</object>
	<object>
		<name>cauliflower</name>
		<pose>Unspecified</pose>
		<truncated>0</truncated>
		<difficult>0</difficult>
		<bndbox>
			<xmin>1465</xmin>
			<ymin>456</ymin>
			<xmax>1697</xmax>
			<ymax>666</ymax>
		</bndbox>
	</object>
	<object>
		<name>carrot</name>
		<pose>Unspecified</pose>
		<truncated>0</truncated>
		<difficult>0</difficult>
		<bndbox>
			<xmin>994</xmin>
			<ymin>55</ymin>
			<xmax>1152</xmax>
			<ymax>263</ymax>
		</bndbox>
	</object>
	<object>
		<name>strawberry</name>
		<pose>Unspecified</pose>
		<truncated>0</truncated>
		<difficult>0</difficult>
		<bndbox>
			<xmin>450</xmin>
			<ymin>258</ymin>
			<xmax>700</xmax>
			<ymax>583</ymax>
		</bndbox>
	</object>
	<object>
		<name>strawberry</name>
		<pose>Unspecified</pose>
		<truncated>0</truncated>
		<difficult>0</difficult>
		<bndbox>
			<xmin>690</xmin>
			<ymin>611</ymin>
			<xmax>954</xmax>
			<ymax>928</ymax>
		</bndbox>
	</object>
</annotation>
